Metadata-Version: 1.0
Name: standard-statistical-distributions
Version: 0.1
Summary: A simple package for Gaussian and Binomial Distributions
Home-page: UNKNOWN
Author: Chi Bui
Author-email: chibui191@gmail.com
License: UNKNOWN
Platform: UNKNOWN
